{
    "incident": [
        {
            "incidentId": 100,
            "category": "Collision with other ship",
            "location": "Outer Anchorage Alfa",
            "shipname": "MV Augusta",
            "description": "description here..",
            "datetime": "2019-11-04T18:02:02.000Z"
        },
        {
            "incidentId": 101,
            "category": "Collision with other ship",
            "location": "Outer Anchorage Alfa",
            "shipname": "MV Augusta",
            "description": "description here..",
            "datetime": "2019-11-04T18:02:02.000Z"
        },
         {
            "incidentId": 102,
            "category": "Collision with other ship",
            "location": "Outer Anchorage Alfa",
            "shipname": "MV Augusta",
            "description": "description here..",
            "datetime": "2019-11-04T18:02:02.000Z"
        },
         {
            "incidentId": 103,
            "category": "Collision with other ship",
            "location": "Outer Anchorage Alfa",
            "shipname": "MV Augusta",
            "description": "description here..",
            "datetime": "2019-11-04T18:02:02.000Z"
        }
    ]
}
